{
  "version": "0.1.20260430",
  "status_code": 20000,
  "status_message": "Ok.",
  "time": "2.0440 sec.",
  "cost": 0.0035,
  "tasks_count": 1,
  "tasks_error": 0,
  "tasks": [
    {
      "id": "05120926-3675-0139-0000-dacaafaa9ba1",
      "status_code": 20000,
      "status_message": "Ok.",
      "time": "1.9231 sec.",
      "cost": 0.0035,
      "result_count": 1,
      "path": [
        "v3",
        "serp",
        "google",
        "organic",
        "live",
        "advanced"
      ],
      "data": {
        "api": "serp",
        "function": "live",
        "se": "google",
        "se_type": "organic",
        "keyword": "facebook ads dashboard template",
        "location_code": 2840,
        "language_code": "en",
        "device": "desktop",
        "os": "windows",
        "depth": 20
      },
      "result": [
        {
          "keyword": "facebook ads dashboard template",
          "type": "organic",
          "se_domain": "google.com",
          "location_code": 2840,
          "language_code": "en",
          "check_url": "https://www.google.com/search?q=facebook%20ads%20dashboard%20template&hl=en&gl=US&ie=UTF-8&uule=w+CAIQIFISCQs2MuSEtepUEUK33kOSuTsc",
          "datetime": "2026-05-12 06:26:11 +00:00",
          "spell": null,
          "refinement_chips": null,
          "item_types": [
            "organic",
            "images",
            "video",
            "related_searches"
          ],
          "se_results_count": 17200000,
          "pages_count": 2,
          "items_count": 22,
          "items": [
            {
              "type": "organic",
              "rank_group": 1,
              "rank_absolute": 1,
              "page": 1,
              "position": "left",
              "xpath": "/html[1]/body[1]/div[3]/div[1]/div[12]/div[1]/div[2]/div[2]/div[1]/div[1]/div[1]/div[1]/div[1]",
              "domain": "www.coupler.io",
              "title": "Meta (Facebook Ads) Dashboard Examples & Reporting ...",
              "url": "https://www.coupler.io/dashboard-examples/facebook-ads-dashboard",
              "cache_url": null,
              "related_search_url": null,
              "breadcrumb": "https://www.coupler.io \u203a Dashboard examples",
              "website_name": "Coupler.io",
              "is_image": false,
              "is_video": false,
              "is_featured_snippet": false,
              "is_malicious": false,
              "is_web_story": false,
              "description": "Track your Facebook Ads performance with automated dashboard templates. Monitor ad spend, conversions, leads, creative performance, and demographic insights\u00a0...",
              "pre_snippet": null,
              "extended_snippet": null,
              "images": null,
              "amp_version": false,
              "rating": null,
              "price": null,
              "highlighted": [
                "automated dashboard templates"
              ],
              "links": null,
              "faq": null,
              "extended_people_also_search": null,
              "about_this_result": null,
              "related_result": null,
              "timestamp": null,
              "rectangle": null
            },
            {
              "type": "organic",
              "rank_group": 2,
              "rank_absolute": 2,
              "page": 1,
              "position": "left",
              "xpath": "/html[1]/body[1]/div[3]/div[1]/div[12]/div[1]/div[2]/div[2]/div[1]/div[1]/div[3]/div[1]/div[1]/div[1]",
              "domain": "portermetrics.com",
              "title": "Best Free Facebook Ads dashboard templates (2026)",
              "url": "https://portermetrics.com/en/dashboard-templates/facebook-ads/",
              "cache_url": null,
              "related_search_url": null,
              "breadcrumb": "https://portermetrics.com \u203a dashboard-templates \u203a faceb...",
              "website_name": "portermetrics.com",
              "is_image": false,
              "is_video": false,
              "is_featured_snippet": false,
              "is_malicious": false,
              "is_web_story": false,
              "description": "Automate your Facebook Ads reporting with our free, white-label dashboard templates, in less than 5 minutes. Used by marketers in +60 countries.",
              "pre_snippet": null,
              "extended_snippet": null,
              "images": null,
              "amp_version": false,
              "rating": null,
              "price": null,
              "highlighted": [
                "free, white-label dashboard templates"
              ],
              "links": null,
              "faq": null,
              "extended_people_also_search": null,
              "about_this_result": null,
              "related_result": null,
              "timestamp": null,
              "rectangle": null
            },
            {
              "type": "organic",
              "rank_group": 3,
              "rank_absolute": 3,
              "page": 1,
              "position": "left",
              "xpath": "/html[1]/body[1]/div[3]/div[1]/div[12]/div[1]/div[2]/div[2]/div[1]/div[1]/div[3]/div[3]/div[1]/div[1]",
              "domain": "amplitude.com",
              "title": "Facebook Ads Dashboard Template",
              "url": "https://amplitude.com/templates/facebook-ads-dashboard",
              "cache_url": null,
              "related_search_url": null,
              "breadcrumb": "https://amplitude.com \u203a templates \u203a facebook-ads-dashb...",
              "website_name": "Amplitude",
              "is_image": false,
              "is_video": false,
              "is_featured_snippet": false,
              "is_malicious": false,
              "is_web_story": false,
              "description": "Our Facebook Ads dashboard helps you track ad impressions, conversions, and ROAS by analyzing ad performance in Amplitude. Read more",
              "pre_snippet": null,
              "extended_snippet": null,
              "images": null,
              "amp_version": false,
              "rating": null,
              "price": null,
              "highlighted": [
                "track ad impressions, conversions, and ROAS"
              ],
              "links": null,
              "faq": null,
              "extended_people_also_search": null,
              "about_this_result": null,
              "related_result": null,
              "timestamp": null,
              "rectangle": null
            },
            {
              "type": "images",
              "rank_group": 1,
              "rank_absolute": 4,
              "page": 1,
              "position": "left",
              "xpath": "/html[1]/body[1]/div[3]/div[1]/div[12]/div[1]/div[2]/div[2]/div[1]/div[1]/div[3]/div[5]/div[1]",
              "title": "Images",
              "url": "https://www.google.com/search?sca_esv=89f358ba4e2fcd04&hl=en&gl=US&q=facebook+ads+dashboard+template&udm=2&source=univ&fir=P770lvsbXAdtNM%252CO81H7hOg7QuDiM%252C_%253BAvd8QNKZvB4RMM%252C8h90PKROF-E0jM%252C_%253Bb6Y3ue_cwQR3xM%252CJNCPjNiL3c-vGM%252C_%253BGpaXHMvmaXEuHM%252CS8L7-yPdEOuCDM%252C_%253Ben7vWx6sziNEqM%252CI8m7FDKn6uNBmM%252C_%253BdZQPe9mYt3kVDM%252CmNKjcnqQluHW0M%252C_%253BMCpa2uNdIpKqPM%252CJNCPjNiL3c-vGM%252C_%253Bc5BZ-iCigmiJoM%252CSW7WN6InY_tfhM%252C_%253BnNejkV4MiyvrYM%252Cejm-tgSuHZ_cvM%252C_%253BA9uqtnCLjRNV9M%252ChzostEO4j1lmbM%252C_%253Bldz3kUfSS_RvaM%252CMrLJd3OxgAIJdM%252C_%253B1z4fifQxpWeY4M%252Cr5zFFJmqhwR1JM%252C_&usg=AI4_-kTq4cu1eCjL7ildZxXTbNxKD8jDpw&sa=X&ved=2ahUKEwi29OuCj7OUAxXZQfEDHbn5OGoQ7Al6BAgcEAU",
              "items": [
                {
                  "type": "images_element",
                  "alt": "Facebook Ads Dashboard Template for Marketers | Whatagraph",
                  "url": "https://whatagraph.com/templates/facebook-ads-dashboard",
                  "image_url": "https://api.dataforseo.com/cdn/i/05120926-3675-0139-0000-dacaafaa9ba1:0"
                },
                {
                  "type": "images_element",
                  "alt": "Facebook Ads Reporting Dashboard Template Walkthrough for Google Sheets &  Google Data Studio",
                  "url": "https://www.youtube.com/watch?v=yrsvw2sO5uQ",
                  "image_url": "https://api.dataforseo.com/cdn/i/05120926-3675-0139-0000-dacaafaa9ba1:1"
                },
                {
                  "type": "images_element",
                  "alt": "Best Free Facebook Ads dashboard templates (2026)",
                  "url": "https://portermetrics.com/en/dashboard-templates/facebook-ads/",
                  "image_url": "https://api.dataforseo.com/cdn/i/05120926-3675-0139-0000-dacaafaa9ba1:2"
                },
                {
                  "type": "images_element",
                  "alt": "21 Looker Studio Facebook Ads Templates to Try in 2026 ...",
                  "url": "https://blog.coupler.io/looker-studio-facebook-ads-templates/",
                  "image_url": "https://api.dataforseo.com/cdn/i/05120926-3675-0139-0000-dacaafaa9ba1:3"
                },
                {
                  "type": "images_element",
                  "alt": "Free Facebook Ads Budget Dashboard Template for Looker Studio",
                  "url": "https://windsor.ai/facebook-ads-budget-dashboard-looker-studio/",
                  "image_url": "https://api.dataforseo.com/cdn/i/05120926-3675-0139-0000-dacaafaa9ba1:4"
                },
                {
                  "type": "images_element",
                  "alt": "Facebook+Google Ads report Google Data Studio - Catchr",
                  "url": "https://www.catchr.io/template/looker-studio-templates/facebook-ads-google-ads-template",
                  "image_url": "https://api.dataforseo.com/cdn/i/05120926-3675-0139-0000-dacaafaa9ba1:5"
                },
                {
                  "type": "images_element",
                  "alt": "Best Free Facebook Ads dashboard templates (2026)",
                  "url": "https://portermetrics.com/en/dashboard-templates/facebook-ads/",
                  "image_url": "https://encrypted-tbn0.gstatic.com/images?q=tbn:ANd9GcQudzsS7N27Ofu3QSX4GQHAh_3ASmRYVjhTPDRJo7wz3bMaz_B67lZYP5c&s"
                },
                {
                  "type": "images_element",
                  "alt": "Data Report: Facebook Ads PPC dashboard - Ad Spend",
                  "url": "https://www.octoboard.com/ppc-reporting-tool/facebook-ads-automated-reports/facebook-ads-ppc-dashboard-using-ad-spend-data",
                  "image_url": "https://encrypted-tbn0.gstatic.com/images?q=tbn:ANd9GcQ2qoCOUgPaXxIy95wzMBg92MFJ_QJjVAcpsiNOvZ0sKMzyeuhluAWPXnw&s"
                },
                {
                  "type": "images_element",
                  "alt": "Facebook Ads Reporting Dashboard & Templates | Klipfolio",
                  "url": "https://www.klipfolio.com/resources/dashboard-examples/social-media/facebook-ads-dashboard",
                  "image_url": "https://encrypted-tbn0.gstatic.com/images?q=tbn:ANd9GcQ4-ttu1q_dupw89gR_psDRyxFyOvevkaT6nnpIo901I8g3idnoaeNdzQo&s"
                },
                {
                  "type": "images_element",
                  "alt": "Free Facebook Ads Power BI Dashboard Template",
                  "url": "https://windsor.ai/free-facebook-ads-power-bi-dashboard-template/",
                  "image_url": "https://encrypted-tbn0.gstatic.com/images?q=tbn:ANd9GcSAqGcxV1tqE35SUtNH7Y_nU6UMpqfL0TqWGzIdu3jt1eutgdCn24O56IQ&s"
                },
                {
                  "type": "images_element",
                  "alt": "Facebook Ads Data Studio Template - Data Bloo",
                  "url": "https://www.databloo.com/templates/facebook-ads-looker-studio-template/",
                  "image_url": "https://encrypted-tbn0.gstatic.com/images?q=tbn:ANd9GcRKXS9k4A_NomSg1DQQiKrn9HLbr_5kEuoHNmAQ3Nmj5B--1dLTQLKZZXk&s"
                },
                {
                  "type": "images_element",
                  "alt": "FREE Facebook Ads Dashboard Template - Slingshot",
                  "url": "https://www.slingshotapp.io/templates/facebook-ads-dashboard",
                  "image_url": "https://encrypted-tbn0.gstatic.com/images?q=tbn:ANd9GcQzqyxbGCPdgu4kvCcSJqoyUHYFD_HPjlSCmeVHhqoxfPid4TDVJJyRRWo&s"
                }
              ],
              "related_image_searches": null,
              "rectangle": null
            },
            {
              "type": "video",
              "rank_group": 1,
              "rank_absolute": 5,
              "page": 1,
              "position": "left",
              "xpath": "/html[1]/body[1]/div[3]/div[1]/div[12]/div[1]/div[2]/div[2]/div[1]/div[1]/div[3]/div[7]/div[1]",
              "items": [
                {
                  "type": "video_element",
                  "source": "YouTube \u00b7 Coupler\u2024io Academy",
                  "title": "Facebook Ads Dashboard Templates For Every Occasion",
                  "timestamp": "2024-03-27 00:00:00 +00:00",
                  "url": "https://www.youtube.com/watch?v=eaMF8BaByP0"
                },
                {
                  "type": "video_element",
                  "source": "YouTube \u00b7 Looker Studio dashboards by Gaille Reports",
                  "title": "Free Facebook Ads Dashboard Template for Looker Studio ...",
                  "timestamp": "2025-07-05 00:00:00 +00:00",
                  "url": "https://www.youtube.com/watch?v=oOZ6ycBdfYs&vl=en"
                },
                {
                  "type": "video_element",
                  "source": "YouTube \u00b7 Coupler\u2024io Academy",
                  "title": "Free Facebook Ads dashboard template for Looker Studio ...",
                  "timestamp": "2025-05-16 00:00:00 +00:00",
                  "url": "https://www.youtube.com/shorts/IsHXcn-oA6k"
                }
              ],
              "rectangle": null
            },
            {
              "type": "organic",
              "rank_group": 4,
              "rank_absolute": 6,
              "page": 1,
              "position": "left",
              "xpath": "/html[1]/body[1]/div[3]/div[1]/div[12]/div[1]/div[2]/div[2]/div[1]/div[1]/div[3]/div[9]/div[1]/div[1]",
              "domain": "windsor.ai",
              "title": "Free Facebook Ads Dashboards & Reporting Templates",
              "url": "https://windsor.ai/template-gallery/facebook-ads-dashboard-reports/",
              "cache_url": null,
              "related_search_url": null,
              "breadcrumb": "https://windsor.ai \u203a Free marketing template gallery",
              "website_name": "Windsor.ai",
              "is_image": true,
              "is_video": false,
              "is_featured_snippet": false,
              "is_malicious": false,
              "is_web_story": false,
              "description": "Use Windsor.ai's free Facebook Ads dashboard templates to track your metrics. No complex setup is required when using our dashboards.",
              "pre_snippet": null,
              "extended_snippet": null,
              "images": [
                {
                  "type": "images_element",
                  "alt": "facebook ads dashboard template from windsor.ai",
                  "url": "https://windsor.ai/template-gallery/facebook-ads-dashboard-reports/",
                  "image_url": "https://encrypted-tbn0.gstatic.com/images?q=tbn:ANd9GcTnddY3NehmNyQ3YEB3ivErxQ5q1d1pwsn8BqeHYjtzVnKbKDbpAgsj&usqp=CAE&s"
                }
              ],
              "amp_version": false,
              "rating": null,
              "price": null,
              "highlighted": [
                "free Facebook Ads dashboard templates"
              ],
              "links": null,
              "faq": null,
              "extended_people_also_search": null,
              "about_this_result": null,
              "related_result": null,
              "timestamp": null,
              "rectangle": null
            },
            {
              "type": "organic",
              "rank_group": 5,
              "rank_absolute": 7,
              "page": 1,
              "position": "left",
              "xpath": "/html[1]/body[1]/div[3]/div[1]/div[12]/div[1]/div[2]/div[2]/div[1]/div[1]/div[3]/div[11]/div[1]/div[1]",
              "domain": "funnel.io",
              "title": "Facebook ads dashboard",
              "url": "https://funnel.io/templates/facebook-ads",
              "cache_url": null,
              "related_search_url": null,
              "breadcrumb": "https://funnel.io \u203a templates \u203a facebook-ads",
              "website_name": "Funnel",
              "is_image": false,
              "is_video": false,
              "is_featured_snippet": false,
              "is_malicious": false,
              "is_web_story": false,
              "description": "Anyone can set up a Facebook ads dashboard with Funnel in a few steps, and rely on our robust data connectors to ensure that your numbers are always accurate\u00a0... Read more",
              "pre_snippet": null,
              "extended_snippet": null,
              "images": null,
              "amp_version": false,
              "rating": null,
              "price": null,
              "highlighted": [
                "Anyone can set up a Facebook ads dashboard with Funnel"
              ],
              "links": null,
              "faq": null,
              "extended_people_also_search": null,
              "about_this_result": null,
              "related_result": null,
              "timestamp": null,
              "rectangle": null
            },
            {
              "type": "organic",
              "rank_group": 6,
              "rank_absolute": 8,
              "page": 1,
              "position": "left",
              "xpath": "/html[1]/body[1]/div[3]/div[1]/div[12]/div[1]/div[2]/div[2]/div[1]/div[1]/div[3]/div[13]/div[1]/div[1]",
              "domain": "supermetrics.com",
              "title": "Facebook Ads Report Templates",
              "url": "https://supermetrics.com/blog/facebook-ads-report-template",
              "cache_url": null,
              "related_search_url": null,
              "breadcrumb": "https://supermetrics.com \u203a blog \u203a facebook-ads-report-te...",
              "website_name": "Supermetrics",
              "is_image": false,
              "is_video": false,
              "is_featured_snippet": false,
              "is_malicious": false,
              "is_web_story": false,
              "description": "Jun 25, 2024 \u2014 Discover free Facebook Ads report templates for Google Sheets, Looker Studio, and Excel to enhance your campaign analysis.",
              "pre_snippet": "06/25/2024 00:00:00",
              "extended_snippet": null,
              "images": null,
              "amp_version": false,
              "rating": null,
              "price": null,
              "highlighted": [
                "free Facebook Ads report templates"
              ],
              "links": null,
              "faq": null,
              "extended_people_also_search": null,
              "about_this_result": null,
              "related_result": null,
              "timestamp": "2024-06-25 00:00:00 +00:00",
              "rectangle": null
            },
            {
              "type": "organic",
              "rank_group": 7,
              "rank_absolute": 9,
              "page": 1,
              "position": "left",
              "xpath": "/html[1]/body[1]/div[3]/div[1]/div[12]/div[1]/div[2]/div[2]/div[1]/div[1]/div[3]/div[15]/div[1]/div[1]",
              "domain": "databox.com",
              "title": "Must-Have Facebook Ads Dashboard Examples ... - Databox",
              "url": "https://databox.com/dashboard-examples/facebook-ads-dashboards",
              "cache_url": null,
              "related_search_url": null,
              "breadcrumb": "https://databox.com \u203a dashboard-examples \u203a facebook-...",
              "website_name": "Databox",
              "is_image": true,
              "is_video": false,
              "is_featured_snippet": false,
              "is_malicious": false,
              "is_web_story": false,
              "description": "Analyze spend, clicks, conversions, and audience performance with pre-built Facebook Ads dashboard templates that help marketers optimize campaigns.",
              "pre_snippet": null,
              "extended_snippet": null,
              "images": [
                {
                  "type": "images_element",
                  "alt": "facebook ads dashboard template from databox.com",
                  "url": "https://databox.com/dashboard-examples/facebook-ads-dashboards",
                  "image_url": "https://encrypted-tbn0.gstatic.com/images?q=tbn:ANd9GcSqmn1F19LtPRx_7k-q7ry9wajXR_gZ9_7X9QgYgmXuiUcLyoOMix7a&usqp=CAE&s"
                }
              ],
              "amp_version": false,
              "rating": null,
              "price": null,
              "highlighted": [
                "pre-built Facebook Ads dashboard templates"
              ],
              "links": [
                {
                  "type": "link_element",
                  "title": "Facebook Ads Templates",
                  "description": null,
                  "url": "https://databox.com/dashboard-examples/facebook-ads-dashboards",
                  "domain": "databox.com"
                },
                {
                  "type": "link_element",
                  "title": "E-Commerce Ads Performance...",
                  "description": null,
                  "url": "https://databox.com/dashboard-examples/facebook-ads-dashboards",
                  "domain": "databox.com"
                },
                {
                  "type": "link_element",
                  "title": "Facebook Ads, Google Ads...",
                  "description": null,
                  "url": "https://databox.com/dashboard-examples/facebook-ads-dashboards",
                  "domain": "databox.com"
                }
              ],
              "faq": null,
              "extended_people_also_search": null,
              "about_this_result": null,
              "related_result": null,
              "timestamp": null,
              "rectangle": null
            },
            {
              "type": "organic",
              "rank_group": 8,
              "rank_absolute": 10,
              "page": 1,
              "position": "left",
              "xpath": "/html[1]/body[1]/div[3]/div[1]/div[12]/div[1]/div[2]/div[2]/div[1]/div[1]/div[3]/div[17]/div[1]/div[1]",
              "domain": "whatagraph.com",
              "title": "Facebook Ads Dashboard Template for Marketers",
              "url": "https://whatagraph.com/templates/facebook-ads-dashboard",
              "cache_url": null,
              "related_search_url": null,
              "breadcrumb": "https://whatagraph.com \u203a templates \u203a facebook-ads-das...",
              "website_name": "Whatagraph",
              "is_image": true,
              "is_video": false,
              "is_featured_snippet": false,
              "is_malicious": false,
              "is_web_story": false,
              "description": "Facebook Ads dashboard templates let you track your Facebook Ads performance by clicks, relevance, reach, engagement, and other key metrics. Read more",
              "pre_snippet": null,
              "extended_snippet": null,
              "images": [
                {
                  "type": "images_element",
                  "alt": "facebook ads dashboard template from whatagraph.com",
                  "url": "https://whatagraph.com/templates/facebook-ads-dashboard",
                  "image_url": "https://encrypted-tbn0.gstatic.com/images?q=tbn:ANd9GcQkCnJmk9Jvy4B1daCbjB8z7uxf2PqL6ILjem_gldE&usqp=CAE&s"
                }
              ],
              "amp_version": false,
              "rating": null,
              "price": null,
              "highlighted": [
                "track your Facebook Ads performance"
              ],
              "links": [
                {
                  "type": "link_element",
                  "title": "Organize Your Data",
                  "description": null,
                  "url": "https://whatagraph.com/templates/facebook-ads-dashboard",
                  "domain": "whatagraph.com"
                },
                {
                  "type": "link_element",
                  "title": "Get Actionable Insights With...",
                  "description": null,
                  "url": "https://whatagraph.com/templates/facebook-ads-dashboard",
                  "domain": "whatagraph.com"
                },
                {
                  "type": "link_element",
                  "title": "Keep Clients In The Loop...",
                  "description": null,
                  "url": "https://whatagraph.com/templates/facebook-ads-dashboard",
                  "domain": "whatagraph.com"
                }
              ],
              "faq": null,
              "extended_people_also_search": null,
              "about_this_result": null,
              "related_result": null,
              "timestamp": null,
              "rectangle": null
            },
            {
              "type": "related_searches",
              "rank_group": 1,
              "rank_absolute": 11,
              "page": 1,
              "position": "left",
              "xpath": "/html[1]/body[1]/div[3]/div[1]/div[12]/div[1]/div[3]/div[1]/div[3]/div[1]/div[1]/div[1]/div[1]/div[2]",
              "items": [
                "Facebook ads dashboard template free download",
                "Facebook ads dashboard template free",
                "Facebook ads dashboard template download",
                "Meta Ads dashboard template",
                "Facebook Ads dashboard screenshot",
                "Facebook Ads Manager",
                "Meta Ads dashboard screenshot",
                "Fake Meta Ads dashboard"
              ],
              "rectangle": null
            },
            {
              "type": "organic",
              "rank_group": 9,
              "rank_absolute": 12,
              "page": 2,
              "position": "left",
              "xpath": "/html[1]/body[1]/div[3]/div[1]/div[12]/div[1]/div[2]/div[2]/div[1]/div[1]/div[1]/div[1]/div[1]",
              "domain": "rows.com",
              "title": "Best 10 Facebook Ads Report Templates in 2026 (Updated)",
              "url": "https://rows.com/blog/post/facebook-ads-report-template",
              "cache_url": null,
              "related_search_url": null,
              "breadcrumb": "https://rows.com \u203a blog \u203a post \u203a facebook-ads-report-te...",
              "website_name": "Rows",
              "is_image": true,
              "is_video": false,
              "is_featured_snippet": false,
              "is_malicious": false,
              "is_web_story": false,
              "description": "Oct 7, 2024 \u2014 From Facebook advertising reports to conversion discrepancy reports, many templates abound to help you make sense of all the campaigns you run. Read more",
              "pre_snippet": "10/07/2024 00:00:00",
              "extended_snippet": null,
              "images": [
                {
                  "type": "images_element",
                  "alt": "facebook ads dashboard template from rows.com",
                  "url": "https://rows.com/blog/post/facebook-ads-report-template",
                  "image_url": "https://api.dataforseo.com/cdn/i/05120926-3675-0139-0000-dacaafaa9ba1:6"
                }
              ],
              "amp_version": false,
              "rating": null,
              "price": null,
              "highlighted": [
                "many templates abound"
              ],
              "links": null,
              "faq": null,
              "extended_people_also_search": null,
              "about_this_result": null,
              "related_result": null,
              "timestamp": "2024-10-07 00:00:00 +00:00",
              "rectangle": null
            },
            {
              "type": "organic",
              "rank_group": 10,
              "rank_absolute": 13,
              "page": 2,
              "position": "left",
              "xpath": "/html[1]/body[1]/div[3]/div[1]/div[12]/div[1]/div[2]/div[2]/div[1]/div[1]/div[2]/div[1]/div[1]",
              "domain": "blog.coupler.io",
              "title": "21 Looker Studio Facebook Ads Templates to Try in 2026",
              "url": "https://blog.coupler.io/looker-studio-facebook-ads-templates/",
              "cache_url": null,
              "related_search_url": null,
              "breadcrumb": "https://blog.coupler.io \u203a looker-studio-facebook-ads-te...",
              "website_name": "Coupler.io Blog",
              "is_image": true,
              "is_video": false,
              "is_featured_snippet": false,
              "is_malicious": false,
              "is_web_story": false,
              "description": "Apr 30, 2026 \u2014 Built specifically for lead generation campaigns, this Facebook Ads Data Studio dashboard template tracks how impressions turn into clicks and\u00a0... Read more",
              "pre_snippet": "04/30/2026 00:00:00",
              "extended_snippet": null,
              "images": [
                {
                  "type": "images_element",
                  "alt": "facebook ads dashboard template from blog.coupler.io",
                  "url": "https://blog.coupler.io/looker-studio-facebook-ads-templates/",
                  "image_url": "https://api.dataforseo.com/cdn/i/05120926-3675-0139-0000-dacaafaa9ba1:7"
                }
              ],
              "amp_version": false,
              "rating": null,
              "price": null,
              "highlighted": [
                "Facebook Ads Data Studio dashboard template"
              ],
              "links": null,
              "faq": null,
              "extended_people_also_search": null,
              "about_this_result": null,
              "related_result": null,
              "timestamp": "2026-04-30 00:00:00 +00:00",
              "rectangle": null
            },
            {
              "type": "organic",
              "rank_group": 11,
              "rank_absolute": 14,
              "page": 2,
              "position": "left",
              "xpath": "/html[1]/body[1]/div[3]/div[1]/div[12]/div[1]/div[2]/div[2]/div[1]/div[1]/div[3]/div[1]/div[1]",
              "domain": "www.reddit.com",
              "title": "We built a Meta Ads dashboard in Looker Studio that ...",
              "url": "https://www.reddit.com/r/FacebookAds/comments/1jwm2yx/we_built_a_meta_ads_dashboard_in_looker_studio/",
              "cache_url": null,
              "related_search_url": null,
              "breadcrumb": "4 comments  \u00b7  1 year ago",
              "website_name": "Reddit\u00a0\u00b7\u00a0r/FacebookAds",
              "is_image": false,
              "is_video": false,
              "is_featured_snippet": false,
              "is_malicious": false,
              "is_web_story": false,
              "description": "We just released a new Google Ads dashboard template for Looker Studio\u2014built to make campaign performance easier to see, share, and optimize. Read more",
              "pre_snippet": null,
              "extended_snippet": null,
              "images": null,
              "amp_version": false,
              "rating": null,
              "price": null,
              "highlighted": [
                "Google Ads dashboard template"
              ],
              "links": null,
              "faq": null,
              "extended_people_also_search": null,
              "about_this_result": null,
              "related_result": null,
              "timestamp": null,
              "rectangle": null
            },
            {
              "type": "organic",
              "rank_group": 12,
              "rank_absolute": 15,
              "page": 2,
              "position": "left",
              "xpath": "/html[1]/body[1]/div[3]/div[1]/div[12]/div[1]/div[2]/div[2]/div[1]/div[1]/div[4]/div[1]/div[1]",
              "domain": "www.klipfolio.com",
              "title": "Facebook Ads Reporting Dashboard & Templates",
              "url": "https://www.klipfolio.com/resources/dashboard-examples/social-media/facebook-ads-dashboard",
              "cache_url": null,
              "related_search_url": null,
              "breadcrumb": "https://www.klipfolio.com \u203a resources \u203a social-media",
              "website_name": "Klipfolio",
              "is_image": false,
              "is_video": false,
              "is_featured_snippet": false,
              "is_malicious": false,
              "is_web_story": false,
              "description": "A Facebook Ads dashboard is a visual representation of the metrics and KPIs from your Facebook advertising data.",
              "pre_snippet": null,
              "extended_snippet": null,
              "images": null,
              "amp_version": false,
              "rating": null,
              "price": null,
              "highlighted": [
                "Facebook Ads dashboard",
                "Facebook advertising"
              ],
              "links": null,
              "faq": null,
              "extended_people_also_search": null,
              "about_this_result": null,
              "related_result": null,
              "timestamp": null,
              "rectangle": null
            },
            {
              "type": "organic",
              "rank_group": 13,
              "rank_absolute": 16,
              "page": 2,
              "position": "left",
              "xpath": "/html[1]/body[1]/div[3]/div[1]/div[12]/div[1]/div[2]/div[2]/div[1]/div[1]/div[5]/div[1]/div[1]",
              "domain": "www.canva.com",
              "title": "Free and customizable Facebook ad templates",
              "url": "https://www.canva.com/facebook-ads/templates/",
              "cache_url": null,
              "related_search_url": null,
              "breadcrumb": "https://www.canva.com \u203a Facebook",
              "website_name": "Canva",
              "is_image": false,
              "is_video": false,
              "is_featured_snippet": false,
              "is_malicious": false,
              "is_web_story": false,
              "description": "With Canva's easy-to-use interface and collection of ready-made templates, you can customize your own ads with no prior graphic design experience required. Read more",
              "pre_snippet": null,
              "extended_snippet": null,
              "images": null,
              "amp_version": false,
              "rating": null,
              "price": null,
              "highlighted": [
                "easy-to-use interface and collection of ready-made templates"
              ],
              "links": null,
              "faq": null,
              "extended_people_also_search": null,
              "about_this_result": null,
              "related_result": null,
              "timestamp": null,
              "rectangle": null
            },
            {
              "type": "organic",
              "rank_group": 14,
              "rank_absolute": 17,
              "page": 2,
              "position": "left",
              "xpath": "/html[1]/body[1]/div[3]/div[1]/div[12]/div[1]/div[2]/div[2]/div[1]/div[1]/div[6]/div[1]/div[1]",
              "domain": "improvado.io",
              "title": "Automated Facebook Ads Reporting: The Definitive Guide ...",
              "url": "https://improvado.io/blog/best-facebook-ads-reports-templates",
              "cache_url": null,
              "related_search_url": null,
              "breadcrumb": "https://improvado.io \u203a Blog \u203a Performance",
              "website_name": "Improvado",
              "is_image": false,
              "is_video": false,
              "is_featured_snippet": false,
              "is_malicious": false,
              "is_web_story": false,
              "description": "Apr 30, 2026 \u2014 Facebook Ads performance dashboard built by Improvado AI Agent. Example of a Facebook Ads performance dashboard built by Improvado AI Agent. Read more",
              "pre_snippet": "04/30/2026 00:00:00",
              "extended_snippet": null,
              "images": null,
              "amp_version": false,
              "rating": null,
              "price": null,
              "highlighted": [
                "Facebook Ads performance dashboard"
              ],
              "links": null,
              "faq": null,
              "extended_people_also_search": null,
              "about_this_result": null,
              "related_result": null,
              "timestamp": "2026-04-30 00:00:00 +00:00",
              "rectangle": null
            },
            {
              "type": "organic",
              "rank_group": 15,
              "rank_absolute": 18,
              "page": 2,
              "position": "left",
              "xpath": "/html[1]/body[1]/div[3]/div[1]/div[12]/div[1]/div[2]/div[2]/div[1]/div[1]/div[7]/div[1]/div[1]",
              "domain": "www.catchr.io",
              "title": "Facebook (Meta) Ads Data Studio dashboard template",
              "url": "https://www.catchr.io/template/looker-studio-templates/meta-ads",
              "cache_url": null,
              "related_search_url": null,
              "breadcrumb": "https://www.catchr.io \u203a Looker Studio Template",
              "website_name": "Catchr",
              "is_image": false,
              "is_video": false,
              "is_featured_snippet": false,
              "is_malicious": false,
              "is_web_story": false,
              "description": "Get your free template to follow your Facebook (Meta) Ads and Instagram Ads KPIs. Thinking by marketers for marketers! Get it for free.",
              "pre_snippet": null,
              "extended_snippet": null,
              "images": null,
              "amp_version": false,
              "rating": null,
              "price": null,
              "highlighted": [
                "Get your free template"
              ],
              "links": null,
              "faq": null,
              "extended_people_also_search": null,
              "about_this_result": null,
              "related_result": null,
              "timestamp": null,
              "rectangle": null
            },
            {
              "type": "organic",
              "rank_group": 16,
              "rank_absolute": 19,
              "page": 2,
              "position": "left",
              "xpath": "/html[1]/body[1]/div[3]/div[1]/div[12]/div[1]/div[2]/div[2]/div[1]/div[1]/div[8]/div[1]/div[1]",
              "domain": "www.notion.com",
              "title": "Facebook Ads Dashboard Template by Lucas's notions",
              "url": "https://www.notion.com/templates/facebook-ads-dashboard?srsltid=AfmBOoomzE8w21FpLuhoBc-bU1VI4Kv_fmZDlRGZ4Dzhsn3bVDAivn6m",
              "cache_url": null,
              "related_search_url": null,
              "breadcrumb": "https://www.notion.com \u203a templates \u203a facebook-ads-das...",
              "website_name": "Notion",
              "is_image": false,
              "is_video": false,
              "is_featured_snippet": false,
              "is_malicious": false,
              "is_web_story": false,
              "description": "Facebook Ads Dashboard is the ultimate command center for your digital marketing strategy. Campaigns Database, Ads Database, Performance Hub, Objectives\u00a0... Read more",
              "pre_snippet": null,
              "extended_snippet": null,
              "images": null,
              "amp_version": false,
              "rating": null,
              "price": {
                "current": 36,
                "regular": null,
                "max_value": null,
                "currency": "USD",
                "is_price_range": false,
                "displayed_price": "$36.00"
              },
              "highlighted": [
                "Facebook Ads Dashboard"
              ],
              "links": null,
              "faq": null,
              "extended_people_also_search": null,
              "about_this_result": null,
              "related_result": null,
              "timestamp": null,
              "rectangle": null
            },
            {
              "type": "organic",
              "rank_group": 17,
              "rank_absolute": 20,
              "page": 2,
              "position": "left",
              "xpath": "/html[1]/body[1]/div[3]/div[1]/div[12]/div[1]/div[2]/div[2]/div[1]/div[1]/div[9]/div[1]/div[1]",
              "domain": "www.slingshotapp.io",
              "title": "FREE Facebook Ads Dashboard Template - Slingshot",
              "url": "https://www.slingshotapp.io/templates/facebook-ads-dashboard",
              "cache_url": null,
              "related_search_url": null,
              "breadcrumb": "https://www.slingshotapp.io \u203a Templates",
              "website_name": "slingshotapp.io",
              "is_image": false,
              "is_video": false,
              "is_featured_snippet": false,
              "is_malicious": false,
              "is_web_story": false,
              "description": "Slingshot's Facebook Ads Dashboard Template gives you a real-time view of your campaign performance. It includes everything from dynamic real-time\u00a0... Read more",
              "pre_snippet": null,
              "extended_snippet": null,
              "images": null,
              "amp_version": false,
              "rating": null,
              "price": null,
              "highlighted": [
                "Slingshot's Facebook Ads Dashboard Template"
              ],
              "links": null,
              "faq": null,
              "extended_people_also_search": null,
              "about_this_result": null,
              "related_result": null,
              "timestamp": null,
              "rectangle": null
            },
            {
              "type": "organic",
              "rank_group": 18,
              "rank_absolute": 21,
              "page": 2,
              "position": "left",
              "xpath": "/html[1]/body[1]/div[3]/div[1]/div[12]/div[1]/div[2]/div[2]/div[1]/div[1]/div[10]/div[1]/div[1]",
              "domain": "coefficient.io",
              "title": "Free Facebook Ads Dashboards for Google Sheets - Coefficient",
              "url": "https://coefficient.io/dashboard-examples/facebook-ads",
              "cache_url": null,
              "related_search_url": null,
              "breadcrumb": "https://coefficient.io \u203a dashboard-examples \u203a facebook-...",
              "website_name": "coefficient.io",
              "is_image": false,
              "is_video": false,
              "is_featured_snippet": false,
              "is_malicious": false,
              "is_web_story": false,
              "description": "Facebook Ads - Free & Make Reporting Easy. Launch pre-built Facebook Ads templates and reports in Google Sheets and connect your live data instantly.",
              "pre_snippet": null,
              "extended_snippet": null,
              "images": null,
              "amp_version": false,
              "rating": {
                "rating_type": "Max5",
                "value": 4.9,
                "votes_count": 574,
                "rating_max": 5
              },
              "price": null,
              "highlighted": [
                "pre-built Facebook Ads templates and reports in Google Sheets"
              ],
              "links": null,
              "faq": null,
              "extended_people_also_search": null,
              "about_this_result": null,
              "related_result": null,
              "timestamp": null,
              "rectangle": null
            },
            {
              "type": "related_searches",
              "rank_group": 2,
              "rank_absolute": 22,
              "page": 2,
              "position": "left",
              "xpath": "/html[1]/body[1]/div[3]/div[1]/div[12]/div[1]/div[3]/div[1]/div[3]/div[1]/div[1]/div[1]/div[1]/div[2]",
              "items": [
                "Facebook ads dashboard template free download",
                "Facebook ads dashboard template free",
                "Facebook ads dashboard template download",
                "Meta Ads dashboard template",
                "Facebook Ads dashboard screenshot",
                "Facebook Ads Manager",
                "Meta Ads dashboard screenshot",
                "Fake Meta Ads dashboard"
              ],
              "rectangle": null
            }
          ]
        }
      ]
    }
  ]
}